package_changtt/__init__.py
package_changtt/第19节  模拟生成数据20250906.py
package_changtt-1.0.0.dist-info/licenses/LICENSE
package_changtt-1.0.0.dist-info/METADATA
package_changtt-1.0.0.dist-info/WHEEL
package_changtt-1.0.0.dist-info/top_level.txt
package_changtt-1.0.0.dist-info/RECORD
